{
  "word": "메모리얼",
  "question": "자녀가 '메모리얼'이라고 했다면 무슨 뜻일까요?",
  "options": [
    "기념할 만한 일이나 장소",
    "과거의 기억을 떠올리는 것",
    "특별한 순간을 축하하는 것",
    "아름다운 경치를 감상하는 것"
  ],
  "answer_index": 0,
  "explanation": "'메모리얼'은 영어 'memorial'에서 유래된 말로, 기념할 만한 일이나 장소를 뜻해요. 특정 사건이나 인물을 기억하고 기리기 위해 만들어진 장소나 행사를 의미합니다. 예를 들어 '그 친구의 메모리얼 파티를 열었어'라는 말은 친구를 기념하는 특별한 자리를 마련했다는 뜻이에요. '메모리얼 데이'는 특정 기억을 기리는 날을 나타내는 표현으로, 사람들의 마음 속에 남아 있는 소중한 기억을 기념하는 의미를 담고 있습니다.",
  "reward_card": {
    "message": "소중한 추억들을 함께 기리자!",
    "background_mood": "warm"
  }
}